settings/__init__.py
settings/defaults.py
settings/local-dist.py
settings/local.py
osf_pigeon-0.0.2.dist-info/LICENSE
osf_pigeon-0.0.2.dist-info/METADATA
osf_pigeon-0.0.2.dist-info/WHEEL
osf_pigeon-0.0.2.dist-info/top_level.txt
osf_pigeon-0.0.2.dist-info/RECORD
