Metadata-Version: 2.1
Name: osf-pigeon
Version: 0.0.2
Summary: A utility for archiving osf storage projects at archive.org
Home-page: https://github.com/CenterForOpenScience/osf-pigeon
Author: Center for Open Science
Author-email: contact@cos.io
License: UNKNOWN
Platform: UNKNOWN
Classifier: Natural Language :: English
Classifier: Intended Audience :: Developers
Classifier: Programming Language :: Python :: 3.7
Classifier: License :: OSI Approved :: MIT License
Classifier: Operating System :: OS Independent
Provides: osf_pigeon
Requires-Dist: bagit (==1.7.0)
Requires-Dist: datacite (==1.0.1)
Requires-Dist: internetarchive (==1.9.4)
Requires-Dist: ratelimit (==2.2.1)
Requires-Dist: requests (==2.24.0)
